mathpy/__init__.py
mathpy/__main__.py
mathpy/builtin_functions.py
mathpy/common.py
mathpy/errors.py
mathpy/interpreter.py
mathpy/lexer.py
mathpy/parser.py
mathpy/parser_nodes.py
mathpy/shell_commands.py
mathpy/tokens.py
mathpy/types.py
mathpy/language_grammar/keywords.json
mathpy/language_grammar/token_types.json
mathpy_string-1.1.dist-info/METADATA
mathpy_string-1.1.dist-info/WHEEL
mathpy_string-1.1.dist-info/top_level.txt
mathpy_string-1.1.dist-info/RECORD
