Metadata-Version: 2.1
Name: mathpy-string
Version: 1.1
Summary: MathPy Project Programming language
Author: Joyful-Bard
Author-email: <thisis@notarealemail.com>
Keywords: mathpy,script,language
Classifier: Intended Audience :: Developers
Classifier: Programming Language :: Python :: 3
Classifier: Operating System :: Microsoft :: Windows
